st2auth_pam_backend/__init__.py
st2auth_pam_backend/pam_backend.py
st2auth_pam_backend/pam_ffi.py
tests/__init__.py
tests/integration/__init__.py
tests/integration/test_authenticate.py
st2_auth_backend_pam-0.4.0.dist-info/LICENSE
st2_auth_backend_pam-0.4.0.dist-info/METADATA
st2_auth_backend_pam-0.4.0.dist-info/WHEEL
st2_auth_backend_pam-0.4.0.dist-info/entry_points.txt
st2_auth_backend_pam-0.4.0.dist-info/top_level.txt
st2_auth_backend_pam-0.4.0.dist-info/RECORD
